vessel_manoeuvring_models/EKF_VMM_1d.py
vessel_manoeuvring_models/EKF_example_ball_drop.py
vessel_manoeuvring_models/EKF_multiple_sensors.py
vessel_manoeuvring_models/KF_multiple_sensors.py
vessel_manoeuvring_models/__init__.py
vessel_manoeuvring_models/accelerometers6.py
vessel_manoeuvring_models/angles.py
vessel_manoeuvring_models/apparent_wind.py
vessel_manoeuvring_models/bias_variance_tradeoff.py
vessel_manoeuvring_models/bis_system.py
vessel_manoeuvring_models/differentiation.py
vessel_manoeuvring_models/equation_helpers.py
vessel_manoeuvring_models/equations.py
vessel_manoeuvring_models/extended_kalman_filter.py
vessel_manoeuvring_models/extended_kalman_vmm.py
vessel_manoeuvring_models/feature_selection.py
vessel_manoeuvring_models/kalman_filter.py
vessel_manoeuvring_models/linear_vmm_equations.py
vessel_manoeuvring_models/linear_vmm_simplified_equations.py
vessel_manoeuvring_models/logger.py
vessel_manoeuvring_models/mlflow_utils.py
vessel_manoeuvring_models/nonlinear_abkowitz_vmm_equations.py
vessel_manoeuvring_models/nonlinear_martin_vmm_equations.py
vessel_manoeuvring_models/nonlinear_vmm_equations.py
vessel_manoeuvring_models/notebook_to_latex.py
vessel_manoeuvring_models/parameter_helpers.py
vessel_manoeuvring_models/parameters.py
vessel_manoeuvring_models/prime_system.py
vessel_manoeuvring_models/reference_frames.py
vessel_manoeuvring_models/substitute_dynamic_symbols.py
vessel_manoeuvring_models/symbols.py
vessel_manoeuvring_models/system_equations.py
vessel_manoeuvring_models/to_mlflow.py
vessel_manoeuvring_models/twin_simulations.py
vessel_manoeuvring_models/vct_scaling.py
vessel_manoeuvring_models/vmm_equations_VCT.py
vessel_manoeuvring_models/data/.gitkeep
vessel_manoeuvring_models/data/__init__.py
vessel_manoeuvring_models/data/case_0.py
vessel_manoeuvring_models/data/case_1.py
vessel_manoeuvring_models/data/kalman_filter.py
vessel_manoeuvring_models/data/lowpass_filter.py
vessel_manoeuvring_models/data/make_dataset.py
vessel_manoeuvring_models-0.0.22.dist-info/METADATA
vessel_manoeuvring_models-0.0.22.dist-info/WHEEL
vessel_manoeuvring_models-0.0.22.dist-info/licenses/LICENSE
vessel_manoeuvring_models-0.0.22.dist-info/RECORD
